tuf/__init__.py
tuf/py.typed
tuf/api/__init__.py
tuf/api/_payload.py
tuf/api/dsse.py
tuf/api/exceptions.py
tuf/api/metadata.py
tuf/api/serialization/__init__.py
tuf/api/serialization/json.py
tuf/ngclient/README.md
tuf/ngclient/__init__.py
tuf/ngclient/config.py
tuf/ngclient/fetcher.py
tuf/ngclient/updater.py
tuf/ngclient/_internal/__init__.py
tuf/ngclient/_internal/requests_fetcher.py
tuf/ngclient/_internal/trusted_metadata_set.py
tuf/repository/__init__.py
tuf/repository/_repository.py
tuf-5.0.0.dist-info/METADATA
tuf-5.0.0.dist-info/WHEEL
tuf-5.0.0.dist-info/licenses/LICENSE
tuf-5.0.0.dist-info/licenses/LICENSE-MIT
tuf-5.0.0.dist-info/RECORD
