Metadata-Version: 2.3
Name: tuf
Version: 5.0.0
Summary: A secure updater framework for Python
Project-URL: Documentation, https://theupdateframework.readthedocs.io/en/stable/
Project-URL: Homepage, https://www.updateframework.com
Project-URL: Issues, https://github.com/theupdateframework/python-tuf/issues
Project-URL: Source, https://github.com/theupdateframework/python-tuf
Author-email: theupdateframework@googlegroups.com
License: MIT OR Apache-2.0
License-File: LICENSE
License-File: LICENSE-MIT
Keywords: authentication,compromise,key,revocation,secure,update,updater
Classifier: Development Status :: 5 - Production/Stable
Classifier: Intended Audience :: Developers
Classifier: License :: OSI Approved :: Apache Software License
Classifier: License :: OSI Approved :: MIT License
Classifier: Natural Language :: English
Classifier: Operating System :: MacOS :: MacOS X
Classifier: Operating System :: Microsoft :: Windows
Classifier: Operating System :: POSIX
Classifier: Operating System :: POSIX :: Linux
Classifier: Programming Language :: Python
Classifier: Programming Language :: Python :: 3
Classifier: Programming Language :: Python :: 3.8
Classifier: Programming Language :: Python :: 3.9
Classifier: Programming Language :: Python :: 3.10
Classifier: Programming Language :: Python :: 3.11
Classifier: Programming Language :: Python :: 3.12
Classifier: Programming Language :: Python :: Implementation :: CPython
Classifier: Topic :: Security
Classifier: Topic :: Software Development
Requires-Python: >=3.8
Requires-Dist: requests>=2.19.1
Requires-Dist: securesystemslib~=1.0
